pbi_parsers/__init__.py
pbi_parsers/base/__init__.py
pbi_parsers/base/lexer.py
pbi_parsers/base/tokens.py
pbi_parsers/dax/__init__.py
pbi_parsers/dax/formatter.py
pbi_parsers/dax/lexer.py
pbi_parsers/dax/main.py
pbi_parsers/dax/parser.py
pbi_parsers/dax/tokens.py
pbi_parsers/dax/utils.py
pbi_parsers/dax/exprs/__init__.py
pbi_parsers/dax/exprs/_base.py
pbi_parsers/dax/exprs/_utils.py
pbi_parsers/dax/exprs/add_sub.py
pbi_parsers/dax/exprs/add_sub_unary.py
pbi_parsers/dax/exprs/array.py
pbi_parsers/dax/exprs/column.py
pbi_parsers/dax/exprs/comparison.py
pbi_parsers/dax/exprs/concatenation.py
pbi_parsers/dax/exprs/div_mul.py
pbi_parsers/dax/exprs/exponent.py
pbi_parsers/dax/exprs/function.py
pbi_parsers/dax/exprs/hierarchy.py
pbi_parsers/dax/exprs/identifier.py
pbi_parsers/dax/exprs/ins.py
pbi_parsers/dax/exprs/keyword.py
pbi_parsers/dax/exprs/literal_number.py
pbi_parsers/dax/exprs/literal_string.py
pbi_parsers/dax/exprs/logical.py
pbi_parsers/dax/exprs/measure.py
pbi_parsers/dax/exprs/none.py
pbi_parsers/dax/exprs/parens.py
pbi_parsers/dax/exprs/returns.py
pbi_parsers/dax/exprs/table.py
pbi_parsers/dax/exprs/variable.py
pbi_parsers/pq/__init__.py
pbi_parsers/pq/formatter.py
pbi_parsers/pq/lexer.py
pbi_parsers/pq/main.py
pbi_parsers/pq/parser.py
pbi_parsers/pq/tokens.py
pbi_parsers/pq/exprs/__init__.py
pbi_parsers/pq/exprs/_base.py
pbi_parsers/pq/exprs/_utils.py
pbi_parsers/pq/exprs/add_sub.py
pbi_parsers/pq/exprs/add_sub_unary.py
pbi_parsers/pq/exprs/and_or_expr.py
pbi_parsers/pq/exprs/array.py
pbi_parsers/pq/exprs/arrow.py
pbi_parsers/pq/exprs/column.py
pbi_parsers/pq/exprs/comparison.py
pbi_parsers/pq/exprs/concatenation.py
pbi_parsers/pq/exprs/div_mul.py
pbi_parsers/pq/exprs/each.py
pbi_parsers/pq/exprs/ellipsis_expr.py
pbi_parsers/pq/exprs/function.py
pbi_parsers/pq/exprs/identifier.py
pbi_parsers/pq/exprs/if_expr.py
pbi_parsers/pq/exprs/is_expr.py
pbi_parsers/pq/exprs/keyword.py
pbi_parsers/pq/exprs/literal_number.py
pbi_parsers/pq/exprs/literal_string.py
pbi_parsers-0.9.5.dist-info/METADATA
pbi_parsers-0.9.5.dist-info/WHEEL
pbi_parsers-0.9.5.dist-info/licenses/LICENSE
pbi_parsers-0.9.5.dist-info/RECORD
