Metadata-Version: 2.4
Name: pbi_parsers
Version: 0.9.5
Summary: Power BI lexer, parsers, and formatters for DAX and M (Power Query) languages
Project-URL: Homepage, https://github.com/douglassimonsen/pbi_parsers
Project-URL: Documentation, https://douglassimonsen.github.io/pbi_parsers/
License-File: LICENSE
Requires-Python: >=3.11.0
Requires-Dist: colorama>=0.4.6
Requires-Dist: jinja2>=3.1.6
Provides-Extra: dev
Requires-Dist: build>=1.2.2; extra == 'dev'
Requires-Dist: coverage; extra == 'dev'
Requires-Dist: coveralls; extra == 'dev'
Requires-Dist: pre-commit>=3.8.0; extra == 'dev'
Requires-Dist: pytest; extra == 'dev'
Requires-Dist: ruff>=0.12.7; extra == 'dev'
Provides-Extra: docs
Requires-Dist: mkdocs-material>=9.6.16; extra == 'docs'
Requires-Dist: mkdocs>=1.6.1; extra == 'docs'
Requires-Dist: mkdocstrings-python>=0.30.0; extra == 'docs'
